vipersci/__init__.py
vipersci/msolo.py
vipersci/nirvss.py
vipersci/nss.py
vipersci/util.py
vipersci/carto/__init__.py
vipersci/carto/accrual.py
vipersci/carto/bounds.py
vipersci/carto/colorforge.py
vipersci/carto/dice_buffer.py
vipersci/carto/dissolve_dice.py
vipersci/carto/dotmap.py
vipersci/carto/get_position.py
vipersci/carto/heatmap.py
vipersci/carto/msolo_simulator.py
vipersci/carto/nirvss_simulator.py
vipersci/carto/nss_modeler.py
vipersci/carto/nss_simulator.py
vipersci/carto/traverse_interpolator.py
vipersci/carto/tri2gpkg.py
vipersci/carto/pds/__init__.py
vipersci/carto/pds/data/__init__.py
vipersci/pds/__init__.py
vipersci/pds/bundle_install.py
vipersci/pds/datetime.py
vipersci/pds/pid.py
vipersci/pds/xml.py
vipersci/pds/labelmaker/__init__.py
vipersci/pds/labelmaker/bundle.py
vipersci/pds/labelmaker/cli.py
vipersci/pds/labelmaker/collection.py
vipersci/pds/labelmaker/generic.py
vipersci/pds/labelmaker/inventory.py
vipersci/vis/__init__.py
vipersci/vis/anaglyph.py
vipersci/vis/anom_pixel.py
vipersci/vis/create_image.py
vipersci/vis/create_mmgis_pano.py
vipersci/vis/create_pano.py
vipersci/vis/create_tif.py
vipersci/vis/header.py
vipersci/vis/image_statistics.py
vipersci/vis/pano_check.py
vipersci/vis/viseer.py
vipersci/vis/db/__init__.py
vipersci/vis/db/create_vis_dbs.py
vipersci/vis/db/image_records.py
vipersci/vis/db/image_requests.py
vipersci/vis/db/image_stats.py
vipersci/vis/db/image_tags.py
vipersci/vis/db/junc_image_pano.py
vipersci/vis/db/junc_image_record_tags.py
vipersci/vis/db/junc_image_req_ldst.py
vipersci/vis/db/ldst.py
vipersci/vis/db/light_records.py
vipersci/vis/db/pano_records.py
vipersci/vis/db/ptu_records.py
vipersci/vis/db/validators.py
vipersci/vis/pds/__init__.py
vipersci/vis/pds/create_browse.py
vipersci/vis/pds/create_pano_product.py
vipersci/vis/pds/create_raw.py
vipersci/vis/pds/data/__init__.py
vipersci-0.11.0.dist-info/AUTHORS.rst
vipersci-0.11.0.dist-info/LICENSE
vipersci-0.11.0.dist-info/METADATA
vipersci-0.11.0.dist-info/WHEEL
vipersci-0.11.0.dist-info/entry_points.txt
vipersci-0.11.0.dist-info/top_level.txt
vipersci-0.11.0.dist-info/RECORD
