Metadata-Version: 2.1
Name: vipersci
Version: 0.11.0
Summary: The VIPER Science package is software to support the activities of the Volatiles Investigating Polar Exploration Rover (VIPER) Science Team.
Home-page: https://github.com/NeoGeographyToolkit/vipersci
Author: vipersci Developers
Author-email: Ross.A.Beyer@nasa.gov
License: Apache 2
Keywords: VIPER
Classifier: Programming Language :: Python :: 3.7
Classifier: Programming Language :: Python :: 3.8
Classifier: Programming Language :: Python :: 3.9
Classifier: License :: OSI Approved :: Apache Software License
Classifier: Operating System :: OS Independent
Classifier: Development Status :: 2 - Pre-Alpha
Classifier: Natural Language :: English
Requires-Python: >=3.7
License-File: LICENSE
License-File: AUTHORS.rst
Requires-Dist: genshi
Requires-Dist: geopandas
Requires-Dist: numpy
Requires-Dist: rasterio
Requires-Dist: pandas
Requires-Dist: psycopg2
Requires-Dist: pyproj
Requires-Dist: scikit-image
Requires-Dist: scikit-learn
Requires-Dist: setuptools
Requires-Dist: shapely
Requires-Dist: sqlalchemy
Requires-Dist: tifftools
